card_deck/__init__.py
card_deck/card_deck.py
card_deck/examples.py
card_deck/model.py
card_deck/tests.py
card_deck-1.2.4.dist-info/LICENSE.txt
card_deck-1.2.4.dist-info/METADATA
card_deck-1.2.4.dist-info/WHEEL
card_deck-1.2.4.dist-info/top_level.txt
card_deck-1.2.4.dist-info/RECORD
