Metadata-Version: 2.1
Name: card-deck
Version: 1.2.4
Summary: An object model of a pack of cards
Home-page: https://github.com/EdmundGoodman/card_deck
Author: Edmund Goodman
Author-email: egoodman3141@gmail.com
License: MIT
Download-URL: https://github.com/EdmundGoodman/card_deck/archive/refs/tags/v1.2.4.tar.gz
Keywords: game,card,model
Platform: UNKNOWN
Classifier: Development Status :: 5 - Production/Stable
Classifier: Intended Audience :: Developers
Classifier: Topic :: Software Development :: Build Tools
Classifier: License :: OSI Approved :: MIT License
Classifier: Programming Language :: Python :: 3
Classifier: Programming Language :: Python :: 3.4
Classifier: Programming Language :: Python :: 3.5
Classifier: Programming Language :: Python :: 3.6
